shipit/__init__.py
shipit/cli.py
shipit/generator.py
shipit/procfile.py
shipit/shipit_types.py
shipit/ui.py
shipit/utils.py
shipit/version.py
shipit/assets/php/php.ini
shipit/assets/wordpress/install.sh
shipit/assets/wordpress/wp-config.php
shipit/builders/__init__.py
shipit/builders/base.py
shipit/builders/docker.py
shipit/builders/local.py
shipit/providers/base.py
shipit/providers/go.py
shipit/providers/hugo.py
shipit/providers/jekyll.py
shipit/providers/laravel.py
shipit/providers/mkdocs.py
shipit/providers/node_static.py
shipit/providers/php.py
shipit/providers/python.py
shipit/providers/registry.py
shipit/providers/staticfile.py
shipit/providers/wordpress.py
shipit/runners/__init__.py
shipit/runners/base.py
shipit/runners/local.py
shipit/runners/wasmer.py
shipit_cli-0.17.1.dist-info/METADATA
shipit_cli-0.17.1.dist-info/WHEEL
shipit_cli-0.17.1.dist-info/entry_points.txt
shipit_cli-0.17.1.dist-info/RECORD
