Metadata-Version: 2.4
Name: shipit-cli
Version: 0.17.1
Summary: Shipit CLI is the best way to build, serve and deploy your projects anywhere.
Project-URL: homepage, https://wasmer.io
Project-URL: repository, https://github.com/wasmerio/shipit
Project-URL: Changelog, https://github.com/wasmerio/shipit/changelog
Requires-Python: >=3.10
Requires-Dist: dotenv>=0.9.9
Requires-Dist: pydantic-settings>=2.12.0
Requires-Dist: pydantic>=2.12.4
Requires-Dist: pyyaml>=6.0.2
Requires-Dist: requests>=2.32.5
Requires-Dist: rich>=14.1.0
Requires-Dist: ripgrep-python>=0.1.0
Requires-Dist: semantic-version>=2.10.0
Requires-Dist: sh>=2.2.2
Requires-Dist: toml>=0.10.2
Requires-Dist: tomlkit>=0.13.3
Requires-Dist: typer>=0.16.1
Requires-Dist: xingque>=0.2.1
